{ "height":15,
 "layers":[
        {
         "data":[20, 18, 18, 18, 18, 18, 18, 18, 18, 18, 18, 18, 18, 18, 21, 11, 30, 30, 30, 30, 30, 30, 30, 30, 30, 30, 30, 32, 30, 9, 11, 30, 30, 30, 30, 30, 30, 30, 30, 30, 30, 30, 30, 32, 9, 11, 30, 30, 30, 30, 30, 30, 30, 30, 30, 30, 30, 30, 30, 9, 11, 38, 48, 30, 30, 30, 30, 30, 30, 30, 30, 30, 30, 30, 9, 11, 40, 31, 30, 30, 30, 30, 30, 30, 30, 30, 30, 30, 30, 9, 11, 30, 30, 30, 30, 30, 30, 30, 30, 30, 30, 30, 30, 30, 9, 11, 30, 30, 30, 30, 30, 30, 30, 30, 30, 30, 30, 30, 30, 9, 11, 30, 30, 30, 30, 30, 30, 30, 30, 30, 30, 30, 30, 30, 9, 11, 30, 30, 30, 30, 30, 30, 30, 30, 30, 30, 30, 30, 30, 9, 11, 30, 30, 30, 30, 30, 30, 30, 30, 30, 30, 30, 30, 30, 9, 11, 30, 30, 30, 30, 30, 30, 30, 30, 30, 30, 30, 30, 30, 9, 11, 30, 30, 30, 30, 30, 30, 30, 30, 30, 30, 30, 30, 30, 9, 11, 30, 30, 30, 30, 30, 30, 30, 30, 30, 30, 30, 30, 30, 9, 28, 2, 2, 2, 2, 2, 2, 2, 2, 2, 2, 2, 2, 2, 29],
         "height":15,
         "name":"Ground",
         "opacity":1,
         "type":"tilelayer",
         "visible":true,
         "width":15,
         "x":0,
         "y":0
        }, 
        {
         "data":[20, 18, 18, 18, 18, 18, 18, 18, 18, 18, 18, 18, 18, 18, 21, 11, 0, 0, 0, 0, 0, 0, 0, 0, 0, 0, 0, 0, 0, 9, 11, 0, 0, 0, 0, 0, 0, 0, 0, 0, 0, 0, 0, 0, 9, 11, 0, 0, 0, 0, 0, 0, 0, 0, 0, 0, 0, 0, 0, 9, 11, 0, 0, 0, 0, 0, 0, 0, 0, 0, 0, 0, 0, 0, 9, 11, 0, 0, 0, 0, 0, 0, 0, 0, 0, 0, 0, 0, 0, 9, 11, 0, 0, 0, 0, 0, 0, 0, 0, 0, 0, 0, 0, 0, 9, 11, 0, 0, 0, 0, 0, 0, 0, 0, 0, 0, 0, 0, 0, 9, 11, 0, 0, 0, 0, 0, 0, 0, 0, 0, 0, 0, 0, 0, 9, 11, 0, 0, 0, 0, 0, 0, 0, 0, 0, 0, 0, 0, 0, 9, 11, 0, 0, 0, 0, 0, 0, 0, 0, 0, 0, 0, 0, 0, 9, 11, 0, 0, 0, 0, 0, 0, 0, 0, 0, 0, 0, 0, 0, 9, 11, 0, 0, 0, 0, 0, 0, 0, 0, 0, 0, 0, 0, 0, 9, 11, 0, 0, 0, 0, 0, 0, 0, 0, 0, 0, 0, 0, 0, 9, 28, 2, 2, 2, 2, 2, 2, 2, 2, 2, 2, 2, 2, 2, 29],
         "height":15,
         "name":"Wall",
         "opacity":1,
         "type":"tilelayer",
         "visible":false,
         "width":15,
         "x":0,
         "y":0
        }],
 "nextobjectid":2,
 "orientation":"orthogonal",
 "renderorder":"right-down",
 "tileheight":32,
 "tilesets":[
        {
         "columns":8,
         "firstgid":1,
         "image":"tiles.png",
         "imageheight":199,
         "imagewidth":265,
         "margin":1,
         "name":"desert",
         "spacing":1,
         "tilecount":48,
         "tileheight":32,
         "tilewidth":32
        }],
 "tilewidth":32,
 "version":1,
 "width":15
}